setup.py
ymci_ext_sloccount/__init__.py
ymci_ext_sloccount/db.py
ymci_ext_sloccount/form.py
ymci_ext_sloccount/routes.py
ymci_ext_sloccount/sloccount.py
ymci_ext_sloccount.egg-info/PKG-INFO
ymci_ext_sloccount.egg-info/SOURCES.txt
ymci_ext_sloccount.egg-info/dependency_links.txt
ymci_ext_sloccount.egg-info/entry_points.txt
ymci_ext_sloccount.egg-info/top_level.txt