Metadata-Version: 1.1
Name: ymci-ext-sloccount
Version: 1.3.0
Summary: Sloccount plugin for ymci
Home-page: UNKNOWN
Author: Clément Plasse, Kozea
Author-email: clement.plasse@kozea.fr
License: UNKNOWN
Platform: Any
Provides: ymci_ext_sloccount
